huaweicloudsdkcbh/__init__.py
huaweicloudsdkcbh/v1/__init__.py
huaweicloudsdkcbh/v1/cbh_async_client.py
huaweicloudsdkcbh/v1/cbh_client.py
huaweicloudsdkcbh/v1/model/__init__.py
huaweicloudsdkcbh/v1/model/availability_zones.py
huaweicloudsdkcbh/v1/model/cbh_instances.py
huaweicloudsdkcbh/v1/model/change_instance_network.py
huaweicloudsdkcbh/v1/model/change_instance_network_request.py
huaweicloudsdkcbh/v1/model/change_instance_network_response.py
huaweicloudsdkcbh/v1/model/change_instance_order_request.py
huaweicloudsdkcbh/v1/model/change_instance_order_response.py
huaweicloudsdkcbh/v1/model/create_cbh_request.py
huaweicloudsdkcbh/v1/model/create_cbh_response.py
huaweicloudsdkcbh/v1/model/create_instance_body.py
huaweicloudsdkcbh/v1/model/create_instance_order.py
huaweicloudsdkcbh/v1/model/create_instance_order_request.py
huaweicloudsdkcbh/v1/model/create_instance_order_response.py
huaweicloudsdkcbh/v1/model/install_cbh_eip_request.py
huaweicloudsdkcbh/v1/model/install_cbh_eip_response.py
huaweicloudsdkcbh/v1/model/instance_detail.py
huaweicloudsdkcbh/v1/model/list_cbh_instance_request.py
huaweicloudsdkcbh/v1/model/list_cbh_instance_response.py
huaweicloudsdkcbh/v1/model/list_quota_status_request.py
huaweicloudsdkcbh/v1/model/list_quota_status_response.py
huaweicloudsdkcbh/v1/model/login_cbh_request.py
huaweicloudsdkcbh/v1/model/login_cbh_request_body.py
huaweicloudsdkcbh/v1/model/login_cbh_response.py
huaweicloudsdkcbh/v1/model/network_request_body.py
huaweicloudsdkcbh/v1/model/nics.py
huaweicloudsdkcbh/v1/model/operate_eip_request_body.py
huaweicloudsdkcbh/v1/model/product_infos.py
huaweicloudsdkcbh/v1/model/public_ip.py
huaweicloudsdkcbh/v1/model/quota_detail.py
huaweicloudsdkcbh/v1/model/reboot_cbh_request_body.py
huaweicloudsdkcbh/v1/model/reboot_type.py
huaweicloudsdkcbh/v1/model/reset_login_method_request.py
huaweicloudsdkcbh/v1/model/reset_login_method_response.py
huaweicloudsdkcbh/v1/model/reset_password.py
huaweicloudsdkcbh-3.1.184.dist-info/METADATA
huaweicloudsdkcbh-3.1.184.dist-info/WHEEL
huaweicloudsdkcbh-3.1.184.dist-info/licenses/LICENSE
huaweicloudsdkcbh-3.1.184.dist-info/RECORD
